<?xml version="1.0" ?>
<file name="D:/workspace/pythonProject/labelTool/data/pic/pic6162.png">
	<level0>
		<point>[(262.01952461799664, 478.4112393887945), (261.1502546689304, 443.64044142614597), (262.8887945670628, 394.09205432937176), (261.1502546689304, 346.28220713073), (265.49660441426147, 293.25674023769096), (270.71222410865875, 230.6693039049236), (276.79711375212224, 200.2448556876061)]</point>
		<branch0>[(262.01952461799664, 478.4112393887945), (261.1502546689304, 443.64044142614597), (262.8887945670628, 394.09205432937176), (261.1502546689304, 346.28220713073), (265.49660441426147, 293.25674023769096), (270.71222410865875, 230.6693039049236), (276.79711375212224, 200.2448556876061)]</branch0>
	</level0>
	<level1>
		<point>[[(259.41171477079797, 345.4129371816638), (248.98047538200342, 317.59629881154495), (224.64091680814943, 296.73382003395585), (215.07894736842104, 275.00207130730047), (200.30135823429544, 250.66251273344648), (183.78522920203739, 235.88492359932087), (159.44567062818334, 218.4995246179966)], [(265.49660441426147, 299.34162988115446), (247.24193548387098, 282.8255008488964), (230.72580645161293, 260.22448217317486), (215.94821731748726, 241.96981324278437), (187.26230899830222, 223.71514431239387)], [(269.8429541595925, 243.70835314091676), (262.01952461799664, 228.93076400679115), (255.93463497453314, 207.19901528013577), (257.6731748726655, 186.33653650254666), (266.3658743633277, 154.17354838709673)], [(267.2351443123939, 243.70835314091676), (285.4898132427844, 228.06149405772493), (307.22156196943973, 224.5844142614601), (332.43039049235995, 221.1073344651952), (348.946519524618, 222.84587436332765)], [(264.62733446519525, 303.6879796264855), (279.4049235993209, 297.603089983022), (301.13667232597624, 285.433310696095), (325.4762308998302, 262.8322920203735), (345.46943972835317, 245.4468930390492), (372.41680814940577, 229.80003395585737), (401.1027164685908, 225.45368421052626)]]</point>
		<branch1 num="0">[(259.41171477079797, 345.4129371816638), (248.98047538200342, 317.59629881154495), (224.64091680814943, 296.73382003395585), (215.07894736842104, 275.00207130730047), (200.30135823429544, 250.66251273344648), (183.78522920203739, 235.88492359932087), (159.44567062818334, 218.4995246179966)]</branch1>
		<branch1 num="1">[(265.49660441426147, 299.34162988115446), (247.24193548387098, 282.8255008488964), (230.72580645161293, 260.22448217317486), (215.94821731748726, 241.96981324278437), (187.26230899830222, 223.71514431239387)]</branch1>
		<branch1 num="2">[(269.8429541595925, 243.70835314091676), (262.01952461799664, 228.93076400679115), (255.93463497453314, 207.19901528013577), (257.6731748726655, 186.33653650254666), (266.3658743633277, 154.17354838709673)]</branch1>
		<branch1 num="3">[(267.2351443123939, 243.70835314091676), (285.4898132427844, 228.06149405772493), (307.22156196943973, 224.5844142614601), (332.43039049235995, 221.1073344651952), (348.946519524618, 222.84587436332765)]</branch1>
		<branch1 num="4">[(264.62733446519525, 303.6879796264855), (279.4049235993209, 297.603089983022), (301.13667232597624, 285.433310696095), (325.4762308998302, 262.8322920203735), (345.46943972835317, 245.4468930390492), (372.41680814940577, 229.80003395585737), (401.1027164685908, 225.45368421052626)]</branch1>
	</level1>
</file>
