<?xml version="1.0" ?>
<file name="D:/workspace/pythonProject/labelTool/data/pic/pic4133.png">
	<level0>
		<point>[(244.6063829787234, 461.0555250514757), (245.48490048043925, 424.1577899794098), (251.63452299245023, 386.381537405628), (262.17673301304046, 309.07199725463283)]</point>
		<branch0>[(244.6063829787234, 461.0555250514757), (245.48490048043925, 424.1577899794098), (251.63452299245023, 386.381537405628), (262.17673301304046, 309.07199725463283)]</branch0>
	</level0>
	<level1>
		<point>[[(249.8774879890185, 384.6245024021963), (231.42862045298557, 345.96973232669876), (213.8582704186685, 308.19347975291697), (182.23164035689774, 248.45428963623885), (154.99759780370624, 171.14474948524366)], [(258.66266300617707, 342.4556623198353), (232.30713795470143, 309.9505147563487), (207.70864790665752, 256.36094715168156), (187.50274536719286, 223.85579958819494)], [(262.17673301304046, 306.4364447494853), (246.3634179821551, 265.1461221688401), (234.94269045984902, 215.07062457103643), (220.88641043239534, 152.69588194921073)], [(259.54118050789293, 307.3149622512011), (278.86856554564173, 271.2957446808511), (304.3455730954015, 217.70617707618396), (325.42999313658197, 180.8084420041181), (375.5054907343857, 124.58332189430337)], [(256.90562800274535, 340.6986273164036), (289.41077556623196, 321.3712422786548), (328.06554564172956, 294.1371997254633), (349.1499656829101, 257.2394646533974), (370.23438572409054, 214.19210706932057), (410.64619080301986, 162.35957446808516)], [(251.63452299245023, 385.5030199039122), (280.6256005490734, 362.6615648593), (301.7100205902539, 346.84824982841457), (334.21516815374054, 342.4556623198353), (402.73953328757716, 339.8201098146877)]]</point>
		<branch1 num="0">[(249.8774879890185, 384.6245024021963), (231.42862045298557, 345.96973232669876), (213.8582704186685, 308.19347975291697), (182.23164035689774, 248.45428963623885), (154.99759780370624, 171.14474948524366)]</branch1>
		<branch1 num="1">[(258.66266300617707, 342.4556623198353), (232.30713795470143, 309.9505147563487), (207.70864790665752, 256.36094715168156), (187.50274536719286, 223.85579958819494)]</branch1>
		<branch1 num="2">[(262.17673301304046, 306.4364447494853), (246.3634179821551, 265.1461221688401), (234.94269045984902, 215.07062457103643), (220.88641043239534, 152.69588194921073)]</branch1>
		<branch1 num="3">[(259.54118050789293, 307.3149622512011), (278.86856554564173, 271.2957446808511), (304.3455730954015, 217.70617707618396), (325.42999313658197, 180.8084420041181), (375.5054907343857, 124.58332189430337)]</branch1>
		<branch1 num="4">[(256.90562800274535, 340.6986273164036), (289.41077556623196, 321.3712422786548), (328.06554564172956, 294.1371997254633), (349.1499656829101, 257.2394646533974), (370.23438572409054, 214.19210706932057), (410.64619080301986, 162.35957446808516)]</branch1>
		<branch1 num="5">[(251.63452299245023, 385.5030199039122), (280.6256005490734, 362.6615648593), (301.7100205902539, 346.84824982841457), (334.21516815374054, 342.4556623198353), (402.73953328757716, 339.8201098146877)]</branch1>
	</level1>
</file>
