<?xml version="1.0" ?>
<file name="C:/Users/YehuZen/Desktop/labelTool/data/pic/pic1420.png">
	<level0>
		<point>[(271.58149405772497, 471.4570797962648), (268.9736842105263, 351.4978268251273)]</point>
		<branch0>[(271.58149405772497, 471.4570797962648), (268.9736842105263, 351.4978268251273)]</branch0>
	</level0>
	<level1>
		<point>[[(268.9736842105263, 350.6285568760611), (246.37266553480475, 340.1973174872665), (215.94821731748726, 322.81191850594223), (171.61544991511033, 321.942648556876), (119.45925297113753, 331.5046179966044)], [(270.71222410865875, 350.6285568760611), (287.2283531409168, 307.1650594227504), (302.8752122241087, 250.66251273344648), (319.39134125636673, 177.6438370118845), (396.75636672325976, 47.25334465195249)], [(268.10441426146014, 348.89001697792867), (268.10441426146014, 288.0411205432937), (259.41171477079797, 222.84587436332765), (254.1960950764007, 174.16675721561967), (246.37266553480475, 25.521595925297106)], [(267.2351443123939, 348.02074702886244), (248.98047538200342, 313.2499490662139), (225.51018675721565, 254.13959252971136), (197.69354838709677, 182.85945670628183), (140.32173174872668, 55.946044142614596)]]</point>
		<branch1 num="0">[(268.9736842105263, 350.6285568760611), (246.37266553480475, 340.1973174872665), (215.94821731748726, 322.81191850594223), (171.61544991511033, 321.942648556876), (119.45925297113753, 331.5046179966044)]</branch1>
		<branch1 num="1">[(270.71222410865875, 350.6285568760611), (287.2283531409168, 307.1650594227504), (302.8752122241087, 250.66251273344648), (319.39134125636673, 177.6438370118845), (396.75636672325976, 47.25334465195249)]</branch1>
		<branch1 num="2">[(268.10441426146014, 348.89001697792867), (268.10441426146014, 288.0411205432937), (259.41171477079797, 222.84587436332765), (254.1960950764007, 174.16675721561967), (246.37266553480475, 25.521595925297106)]</branch1>
		<branch1 num="3">[(267.2351443123939, 348.02074702886244), (248.98047538200342, 313.2499490662139), (225.51018675721565, 254.13959252971136), (197.69354838709677, 182.85945670628183), (140.32173174872668, 55.946044142614596)]</branch1>
	</level1>
</file>
