<?xml version="1.0" ?>
<file name="D:/workspace/pythonProject/labelTool/data/pic/pic6234.png">
	<level0>
		<point>[(263.758064516129, 449.72533106960947), (263.758064516129, 408.8696434634974), (260.2809847198642, 358.45198641765705), (255.93463497453314, 309.772869269949), (253.32682512733447, 266.30937181663836), (255.93463497453314, 233.2771137521222)]</point>
		<branch0>[(263.758064516129, 449.72533106960947), (263.758064516129, 408.8696434634974), (260.2809847198642, 358.45198641765705), (255.93463497453314, 309.772869269949), (253.32682512733447, 266.30937181663836), (255.93463497453314, 233.2771137521222)]</branch0>
	</level0>
	<level1>
		<point>[[(260.2809847198642, 340.1973174872665), (233.33361629881153, 320.2041086587436), (215.07894736842104, 284.56404074702886), (196.82427843803055, 254.13959252971136), (150.75297113752123, 228.06149405772493), (113.37436332767403, 219.36879456706276), (88.16553480475382, 210.67609507640066)], [(255.93463497453314, 318.4655687606112), (237.67996604414265, 299.34162988115446), (206.38624787775893, 246.31616298811542), (189.00084889643466, 205.46047538200338), (158.57640067911717, 160.25843803056023), (137.713921901528, 127.22617996604413)], [(254.1960950764007, 265.44010186757214), (240.28777589134125, 237.62346349745326), (218.55602716468593, 198.50631578947366), (197.69354838709677, 163.73551782682512), (175.09252971137522, 142.87303904923596), (146.40662139219017, 113.31786078098469)], [(252.45755517826825, 231.53857385398976), (238.54923599320887, 201.11412563667227), (228.98726655348048, 176.77456706281833), (211.6018675721562, 141.1344991511035), (193.34719864176571, 106.36370118845497)], [(254.1960950764007, 229.80003395585737), (268.9736842105263, 200.2448556876061), (288.097623089983, 181.1209168081494), (302.8752122241087, 163.73551782682512), (326.34550084889645, 140.26522920203735), (336.776740237691, 123.74910016977924), (349.8157894736842, 92.45538200339558)], [(257.6731748726655, 235.88492359932087), (275.0585738539898, 219.36879456706276), (278.5356536502547, 198.50631578947366), (278.5356536502547, 168.08186757215617), (297.6595925297114, 136.78814940577246), (304.6137521222411, 114.18713073005091)], [(256.8039049235993, 308.0343293718166), (269.8429541595925, 288.0411205432937), (287.2283531409168, 258.4859422750424), (303.7444821731749, 230.6693039049236), (325.4762308998302, 200.2448556876061), (343.7308998302207, 173.29748726655345), (361.116298811545, 135.91887945670624), (394.14855687606115, 95.0631918505942)], [(256.8039049235993, 319.3348387096774), (270.71222410865875, 314.98848896434635), (282.0127334465195, 300.2108998302207), (301.13667232597624, 278.47915110356536), (316.7835314091681, 259.35521222410864), (341.9923599320883, 235.01565365025465), (360.24702886247877, 224.5844142614601), (392.4100169779287, 222.84587436332765), (419.3573853989813, 226.32295415959248), (435.0042444821732, 220.238064516129)]]</point>
		<branch1 num="0">[(260.2809847198642, 340.1973174872665), (233.33361629881153, 320.2041086587436), (215.07894736842104, 284.56404074702886), (196.82427843803055, 254.13959252971136), (150.75297113752123, 228.06149405772493), (113.37436332767403, 219.36879456706276), (88.16553480475382, 210.67609507640066)]</branch1>
		<branch1 num="1">[(255.93463497453314, 318.4655687606112), (237.67996604414265, 299.34162988115446), (206.38624787775893, 246.31616298811542), (189.00084889643466, 205.46047538200338), (158.57640067911717, 160.25843803056023), (137.713921901528, 127.22617996604413)]</branch1>
		<branch1 num="2">[(254.1960950764007, 265.44010186757214), (240.28777589134125, 237.62346349745326), (218.55602716468593, 198.50631578947366), (197.69354838709677, 163.73551782682512), (175.09252971137522, 142.87303904923596), (146.40662139219017, 113.31786078098469)]</branch1>
		<branch1 num="3">[(252.45755517826825, 231.53857385398976), (238.54923599320887, 201.11412563667227), (228.98726655348048, 176.77456706281833), (211.6018675721562, 141.1344991511035), (193.34719864176571, 106.36370118845497)]</branch1>
		<branch1 num="4">[(254.1960950764007, 229.80003395585737), (268.9736842105263, 200.2448556876061), (288.097623089983, 181.1209168081494), (302.8752122241087, 163.73551782682512), (326.34550084889645, 140.26522920203735), (336.776740237691, 123.74910016977924), (349.8157894736842, 92.45538200339558)]</branch1>
		<branch1 num="5">[(257.6731748726655, 235.88492359932087), (275.0585738539898, 219.36879456706276), (278.5356536502547, 198.50631578947366), (278.5356536502547, 168.08186757215617), (297.6595925297114, 136.78814940577246), (304.6137521222411, 114.18713073005091)]</branch1>
		<branch1 num="6">[(256.8039049235993, 308.0343293718166), (269.8429541595925, 288.0411205432937), (287.2283531409168, 258.4859422750424), (303.7444821731749, 230.6693039049236), (325.4762308998302, 200.2448556876061), (343.7308998302207, 173.29748726655345), (361.116298811545, 135.91887945670624), (394.14855687606115, 95.0631918505942)]</branch1>
		<branch1 num="7">[(256.8039049235993, 319.3348387096774), (270.71222410865875, 314.98848896434635), (282.0127334465195, 300.2108998302207), (301.13667232597624, 278.47915110356536), (316.7835314091681, 259.35521222410864), (341.9923599320883, 235.01565365025465), (360.24702886247877, 224.5844142614601), (392.4100169779287, 222.84587436332765), (419.3573853989813, 226.32295415959248), (435.0042444821732, 220.238064516129)]</branch1>
	</level1>
</file>
