<?xml version="1.0" ?>
<file name="D:/workspace/pythonProject/labelTool/data/pic/pic4311.png">
	<level0>
		<point>[(278.86856554564173, 457.54145504461223), (276.23301304049414, 396.92374742621826), (274.4759780370624, 329.2778997940975), (277.99004804392587, 285.3520247083048)]</point>
		<branch0>[(278.86856554564173, 457.54145504461223), (276.23301304049414, 396.92374742621826), (274.4759780370624, 329.2778997940975), (277.99004804392587, 285.3520247083048)]</branch0>
	</level0>
	<level1>
		<point>[[(272.71894303363075, 331.0349347975292), (248.12045298558678, 311.7075497597804), (225.2789979409746, 282.7164722031572), (191.8953328757721, 237.03356211393276), (179.59608785175016, 203.64989704873028), (161.14722031571722, 161.4810569663693)], [(274.4759780370624, 283.59498970487306), (264.81228551818805, 244.0617021276596), (262.17673301304046, 198.37879203843517), (264.81228551818805, 157.08846945778998), (268.32635552505144, 110.52704186684974)], [(273.59746053534656, 284.4735072065889), (288.5322580645161, 262.51056966369254), (305.22409059711737, 223.85579958819494), (328.9440631434454, 193.9862045298559), (349.1499656829101, 178.1728894989705), (372.86993822923813, 140.39663692518877)], [(279.7470830473576, 352.9978723404256), (298.1959505833905, 332.79196980096094), (306.98112560054903, 304.6794097460536), (317.5233356211393, 266.90315717227185), (339.48627316403565, 238.79059711736448), (377.2625257378174, 214.19210706932057), (404.4965682910089, 192.2291695264242), (440.5157858613589, 189.59361702127666)]]</point>
		<branch1 num="0">[(272.71894303363075, 331.0349347975292), (248.12045298558678, 311.7075497597804), (225.2789979409746, 282.7164722031572), (191.8953328757721, 237.03356211393276), (179.59608785175016, 203.64989704873028), (161.14722031571722, 161.4810569663693)]</branch1>
		<branch1 num="1">[(274.4759780370624, 283.59498970487306), (264.81228551818805, 244.0617021276596), (262.17673301304046, 198.37879203843517), (264.81228551818805, 157.08846945778998), (268.32635552505144, 110.52704186684974)]</branch1>
		<branch1 num="2">[(273.59746053534656, 284.4735072065889), (288.5322580645161, 262.51056966369254), (305.22409059711737, 223.85579958819494), (328.9440631434454, 193.9862045298559), (349.1499656829101, 178.1728894989705), (372.86993822923813, 140.39663692518877)]</branch1>
		<branch1 num="3">[(279.7470830473576, 352.9978723404256), (298.1959505833905, 332.79196980096094), (306.98112560054903, 304.6794097460536), (317.5233356211393, 266.90315717227185), (339.48627316403565, 238.79059711736448), (377.2625257378174, 214.19210706932057), (404.4965682910089, 192.2291695264242), (440.5157858613589, 189.59361702127666)]</branch1>
	</level1>
</file>
