<?xml version="1.0" ?>
<file name="C:/Users/YehuZen/Desktop/labelTool/data/pic/pic1463.png">
	<level0>
		<point>[(257.6731748726655, 416.6930730050933), (260.2809847198642, 302.81870967741935)]</point>
		<branch0>[(257.6731748726655, 416.6930730050933), (260.2809847198642, 302.81870967741935)]</branch0>
	</level0>
	<level1>
		<point>[[(260.2809847198642, 301.0801697792869), (279.4049235993209, 274.13280135823425), (300.26740237691, 241.10054329371815), (326.34550084889645, 204.59120543293716), (357.63921901528016, 158.51989813242784), (373.286078098472, 116.79494057724952), (379.3709677419355, 70.7236332767402), (401.97198641765704, 6.397657045840333)], [(261.1502546689304, 300.2108998302207), (264.62733446519525, 247.18543293718164), (267.2351443123939, 172.42821731748722), (277.66638370118847, 115.92567062818335), (285.4898132427844, 62.030933786078094), (295.05178268251274, 4.6591171477080024)], [(258.54244482173175, 301.0801697792869), (235.9414261460102, 282.8255008488964), (211.6018675721562, 238.49273344651948), (184.65449915110355, 203.72193548387094), (156.83786078098473, 168.08186757215617), (143.7988115449915, 129.83398981324274), (140.32173174872668, 9.874736842105222)]]</point>
		<branch1 num="0">[(260.2809847198642, 301.0801697792869), (279.4049235993209, 274.13280135823425), (300.26740237691, 241.10054329371815), (326.34550084889645, 204.59120543293716), (357.63921901528016, 158.51989813242784), (373.286078098472, 116.79494057724952), (379.3709677419355, 70.7236332767402), (401.97198641765704, 6.397657045840333)]</branch1>
		<branch1 num="1">[(261.1502546689304, 300.2108998302207), (264.62733446519525, 247.18543293718164), (267.2351443123939, 172.42821731748722), (277.66638370118847, 115.92567062818335), (285.4898132427844, 62.030933786078094), (295.05178268251274, 4.6591171477080024)]</branch1>
		<branch1 num="2">[(258.54244482173175, 301.0801697792869), (235.9414261460102, 282.8255008488964), (211.6018675721562, 238.49273344651948), (184.65449915110355, 203.72193548387094), (156.83786078098473, 168.08186757215617), (143.7988115449915, 129.83398981324274), (140.32173174872668, 9.874736842105222)]</branch1>
	</level1>
</file>
