<?xml version="1.0" ?>
<file name="D:/workspace/pythonProject/labelTool/data/pic/pic6555.png">
	<level0>
		<point>[(275.0585738539898, 441.9019015280136), (275.0585738539898, 408.0003735144312), (272.4507640067912, 354.10563667232594), (270.71222410865875, 305.42651952461796)]</point>
		<branch0>[(275.0585738539898, 441.9019015280136), (275.0585738539898, 408.0003735144312), (272.4507640067912, 354.10563667232594), (270.71222410865875, 305.42651952461796)]</branch0>
	</level0>
	<level1>
		<point>[[(273.3200339558574, 336.72023769100167), (259.41171477079797, 325.4197283531409), (235.9414261460102, 301.0801697792869), (221.16383701188454, 270.6557215619694), (189.00084889643466, 243.70835314091676), (160.31494057724956, 228.93076400679115), (106.42020373514431, 235.88492359932087)], [(272.4507640067912, 300.2108998302207), (267.2351443123939, 258.4859422750424), (262.8887945670628, 215.0224448217317), (252.45755517826825, 175.9052971137521), (237.67996604414265, 131.57252971137518)], [(268.10441426146014, 305.42651952461796), (282.0127334465195, 284.56404074702886), (310.6986417657046, 251.5317826825127), (335.03820033955856, 230.6693039049236), (359.37775891341255, 201.9833955857385), (388.9329371816639, 190.68288624787772), (421.96519524618, 194.1599660441426)]]</point>
		<branch1 num="0">[(273.3200339558574, 336.72023769100167), (259.41171477079797, 325.4197283531409), (235.9414261460102, 301.0801697792869), (221.16383701188454, 270.6557215619694), (189.00084889643466, 243.70835314091676), (160.31494057724956, 228.93076400679115), (106.42020373514431, 235.88492359932087)]</branch1>
		<branch1 num="1">[(272.4507640067912, 300.2108998302207), (267.2351443123939, 258.4859422750424), (262.8887945670628, 215.0224448217317), (252.45755517826825, 175.9052971137521), (237.67996604414265, 131.57252971137518)]</branch1>
		<branch1 num="2">[(268.10441426146014, 305.42651952461796), (282.0127334465195, 284.56404074702886), (310.6986417657046, 251.5317826825127), (335.03820033955856, 230.6693039049236), (359.37775891341255, 201.9833955857385), (388.9329371816639, 190.68288624787772), (421.96519524618, 194.1599660441426)]</branch1>
	</level1>
</file>
